{
    "$schema": "https://schema.management.azure.com/schemas/2019-04-01/deploymentTemplate.json#",
    "contentVersion": "1.0.0.0",
    "parameters": {
        "kustoClusterName": {
            "defaultValue": "[concat('azmetaade', uniqueString(resourceGroup().id, 'azmetaade'))]",
            "type": "String",
            "metadata": {
                "description": "Globally unique name for the Kusto cluster. Lowercase letters and numbers. Start with letter. 4-22 characters."
            }
        },
        "kustoDatabaseName": {
            "defaultValue": "azmeta",
            "type": "String",
            "metadata": {
                "description": "Name for the azmeta database in your Kusto cluster."
            }
        },
        "forceUpdateTag": {
            "defaultValue": "[utcNow()]",
            "type": "String"
        },
        "storageAccountName": {
            "defaultValue": "[concat('azmetasa', uniqueString(resourceGroup().id, 'azmetasa'))]",
            "type": "String",
            "metadata": {
                "description": "Globally unique name for the storage account. Lowercase letters and numbers. 3-24 characters."
            }
        },
        "dataFactoryName": {
            "defaultValue": "[concat('azmetaadf', uniqueString(resourceGroup().id, 'azmetaadf'))]",
            "type": "String",
            "metadata": {
                "description": "Globally unique name for the data factory. Alphanumerics and hyphens. Start and end with alphanumeric. 3-63 characters."
            }
        },
        "preProduction": {
            "type": "bool",
            "defaultValue": false,
            "metadata": {
                "description": "Deploy for pre-production use. Uses development SKU for Azure Data Explorer."
            }
        },
        "updating": {
            "type": "bool",
            "defaultValue": false,
            "metadata": {
                "description": "Set to true if redeploying the template. Data Factory trigger resources can not be redeployed while they are enabled."
            }
        },
        "kustoIngestClientId": {
            "type": "String",
            "metadata": {
                "description": "The client/app id (not object id) for the service principal that data factory will use to connect to Kusto."
            }
        },
        "kustoIngestClientSecret": {
            "type": "SecureString",
            "metadata": {
                "description": "The client secret for the service principal that data factory will use to connect to Kusto."
            }
        },
        "deploymentIdentity": {
            "type": "String",
            "metadata": {
                "description": "The resource id of the user-assigned managed identity resource to use during deployment."
            }
        }
    },
    "variables": {
        "usageTableTranslator": {
            "type": "TabularTranslator",
            "mappings": [
                {
                    "source": {
                        "name": "InvoiceSectionName",
                        "type": "String"
                    },
                    "sink": {
                        "name": "InvoiceSectionName",
                        "type": "String"
                    }
                },
                {
                    "source": {
                        "name": "AccountName",
                        "type": "String"
                    },
                    "sink": {
                        "name": "AccountName",
                        "type": "String"
                    }
                },
                {
                    "source": {
                        "name": "AccountOwnerId",
                        "type": "String"
                    },
                    "sink": {
                        "name": "AccountOwnerId",
                        "type": "String"
                    }
                },
                {
                    "source": {
                        "name": "SubscriptionId",
                        "type": "String"
                    },
                    "sink": {
                        "name": "SubscriptionId",
                        "type": "String"
                    }
                },
                {
                    "source": {
                        "name": "SubscriptionName",
                        "type": "String"
                    },
                    "sink": {
                        "name": "SubscriptionName",
                        "type": "String"
                    }
                },
                {
                    "source": {
                        "name": "ResourceGroup",
                        "type": "String"
                    },
                    "sink": {
                        "name": "ResourceGroup",
                        "type": "String"
                    }
                },
                {
                    "source": {
                        "name": "ResourceLocation",
                        "type": "String"
                    },
                    "sink": {
                        "name": "ResourceLocation",
                        "type": "String"
                    }
                },
                {
                    "source": {
                        "name": "Date",
                        "type": "String"
                    },
                    "sink": {
                        "name": "Date",
                        "type": "String"
                    }
                },
                {
                    "source": {
                        "name": "ProductName",
                        "type": "String"
                    },
                    "sink": {
                        "name": "ProductName",
                        "type": "String"
                    }
                },
                {
                    "source": {
                        "name": "MeterCategory",
                        "type": "String"
                    },
                    "sink": {
                        "name": "MeterCategory",
                        "type": "String"
                    }
                },
                {
                    "source": {
                        "name": "MeterSubCategory",
                        "type": "String"
                    },
                    "sink": {
                        "name": "MeterSubCategory",
                        "type": "String"
                    }
                },
                {
                    "source": {
                        "name": "MeterId",
                        "type": "String"
                    },
                    "sink": {
                        "name": "MeterId",
                        "type": "String"
                    }
                },
                {
                    "source": {
                        "name": "MeterName",
                        "type": "String"
                    },
                    "sink": {
                        "name": "MeterName",
                        "type": "String"
                    }
                },
                {
                    "source": {
                        "name": "MeterRegion",
                        "type": "String"
                    },
                    "sink": {
                        "name": "MeterRegion",
                        "type": "String"
                    }
                },
                {
                    "source": {
                        "name": "UnitOfMeasure",
                        "type": "String"
                    },
                    "sink": {
                        "name": "UnitOfMeasure",
                        "type": "String"
                    }
                },
                {
                    "source": {
                        "name": "Quantity",
                        "type": "String"
                    },
                    "sink": {
                        "name": "Quantity",
                        "type": "String"
                    }
                },
                {
                    "source": {
                        "name": "EffectivePrice",
                        "type": "String"
                    },
                    "sink": {
                        "name": "EffectivePrice",
                        "type": "String"
                    }
                },
                {
                    "source": {
                        "name": "CostInBillingCurrency",
                        "type": "String"
                    },
                    "sink": {
                        "name": "CostInBillingCurrency",
                        "type": "String"
                    }
                },
                {
                    "source": {
                        "name": "CostCenter",
                        "type": "String"
                    },
                    "sink": {
                        "name": "CostCenter",
                        "type": "String"
                    }
                },
                {
                    "source": {
                        "name": "ConsumedService",
                        "type": "String"
                    },
                    "sink": {
                        "name": "ConsumedService",
                        "type": "String"
                    }
                },
                {
                    "source": {
                        "name": "ResourceId",
                        "type": "String"
                    },
                    "sink": {
                        "name": "ResourceId",
                        "type": "String"
                    }
                },
                {
                    "source": {
                        "name": "Tags",
                        "type": "String"
                    },
                    "sink": {
                        "name": "Tags",
                        "type": "String"
                    }
                },
                {
                    "source": {
                        "name": "OfferId",
                        "type": "String"
                    },
                    "sink": {
                        "name": "OfferId",
                        "type": "String"
                    }
                },
                {
                    "source": {
                        "name": "AdditionalInfo",
                        "type": "String"
                    },
                    "sink": {
                        "name": "AdditionalInfo",
                        "type": "String"
                    }
                },
                {
                    "source": {
                        "name": "ServiceInfo1",
                        "type": "String"
                    },
                    "sink": {
                        "name": "ServiceInfo1",
                        "type": "String"
                    }
                },
                {
                    "source": {
                        "name": "ServiceInfo2",
                        "type": "String"
                    },
                    "sink": {
                        "name": "ServiceInfo2",
                        "type": "String"
                    }
                },
                {
                    "source": {
                        "name": "ResourceName",
                        "type": "String"
                    },
                    "sink": {
                        "name": "ResourceName",
                        "type": "String"
                    }
                },
                {
                    "source": {
                        "name": "ReservationId",
                        "type": "String"
                    },
                    "sink": {
                        "name": "ReservationId",
                        "type": "String"
                    }
                },
                {
                    "source": {
                        "name": "ReservationName",
                        "type": "String"
                    },
                    "sink": {
                        "name": "ReservationName",
                        "type": "String"
                    }
                },
                {
                    "source": {
                        "name": "UnitPrice",
                        "type": "String"
                    },
                    "sink": {
                        "name": "UnitPrice",
                        "type": "String"
                    }
                },
                {
                    "source": {
                        "name": "ProductOrderId",
                        "type": "String"
                    },
                    "sink": {
                        "name": "ProductOrderId",
                        "type": "String"
                    }
                },
                {
                    "source": {
                        "name": "ProductOrderName",
                        "type": "String"
                    },
                    "sink": {
                        "name": "ProductOrderName",
                        "type": "String"
                    }
                },
                {
                    "source": {
                        "name": "Term",
                        "type": "String"
                    },
                    "sink": {
                        "name": "Term",
                        "type": "String"
                    }
                },
                {
                    "source": {
                        "name": "PublisherType",
                        "type": "String"
                    },
                    "sink": {
                        "name": "PublisherType",
                        "type": "String"
                    }
                },
                {
                    "source": {
                        "name": "PublisherName",
                        "type": "String"
                    },
                    "sink": {
                        "name": "PublisherName",
                        "type": "String"
                    }
                },
                {
                    "source": {
                        "name": "ChargeType",
                        "type": "String"
                    },
                    "sink": {
                        "name": "ChargeType",
                        "type": "String"
                    }
                },
                {
                    "source": {
                        "name": "Frequency",
                        "type": "String"
                    },
                    "sink": {
                        "name": "Frequency",
                        "type": "String"
                    }
                },
                {
                    "source": {
                        "name": "PricingModel",
                        "type": "String"
                    },
                    "sink": {
                        "name": "PricingModel",
                        "type": "String"
                    }
                },
                {
                    "source": {
                        "name": "AvailabilityZone",
                        "type": "String"
                    },
                    "sink": {
                        "name": "AvailabilityZone",
                        "type": "String"
                    }
                },
                {
                    "source": {
                        "name": "BillingAccountId",
                        "type": "String"
                    },
                    "sink": {
                        "name": "BillingAccountId",
                        "type": "String"
                    }
                },
                {
                    "source": {
                        "name": "BillingAccountName",
                        "type": "String"
                    },
                    "sink": {
                        "name": "BillingAccountName",
                        "type": "String"
                    }
                },
                {
                    "source": {
                        "name": "BillingCurrencyCode",
                        "type": "String"
                    },
                    "sink": {
                        "name": "BillingCurrencyCode",
                        "type": "String"
                    }
                },
                {
                    "source": {
                        "name": "BillingPeriodStartDate",
                        "type": "String"
                    },
                    "sink": {
                        "name": "BillingPeriodStartDate",
                        "type": "String"
                    }
                },
                {
                    "source": {
                        "name": "BillingPeriodEndDate",
                        "type": "String"
                    },
                    "sink": {
                        "name": "BillingPeriodEndDate",
                        "type": "String"
                    }
                },
                {
                    "source": {
                        "name": "BillingProfileId",
                        "type": "String"
                    },
                    "sink": {
                        "name": "BillingProfileId",
                        "type": "String"
                    }
                },
                {
                    "source": {
                        "name": "BillingProfileName",
                        "type": "String"
                    },
                    "sink": {
                        "name": "BillingProfileName",
                        "type": "String"
                    }
                },
                {
                    "source": {
                        "name": "InvoiceSectionId",
                        "type": "String"
                    },
                    "sink": {
                        "name": "InvoiceSectionId",
                        "type": "String"
                    }
                },
                {
                    "source": {
                        "name": "IsAzureCreditEligible",
                        "type": "String"
                    },
                    "sink": {
                        "name": "IsAzureCreditEligible",
                        "type": "String"
                    }
                },
                {
                    "source": {
                        "name": "PartNumber",
                        "type": "String"
                    },
                    "sink": {
                        "name": "PartNumber",
                        "type": "String"
                    }
                },
                {
                    "source": {
                        "name": "PayGPrice",
                        "type": "String"
                    },
                    "sink": {
                        "name": "PayGPrice",
                        "type": "String"
                    }
                },
                {
                    "source": {
                        "name": "PlanName",
                        "type": "String"
                    },
                    "sink": {
                        "name": "PlanName",
                        "type": "String"
                    }
                },
                {
                    "source": {
                        "name": "ServiceFamily",
                        "type": "String"
                    },
                    "sink": {
                        "name": "ServiceFamily",
                        "type": "String"
                    }
                }
            ]
        },
        "kqlScript":  "[concat('.create-merge table UsagePreliminaryIngest (InvoiceSectionName: string, AccountName: string, AccountOwnerId: string, SubscriptionId: string, SubscriptionName: string, ResourceGroup: string, ResourceLocation: string, Date: datetime, ProductName: string, MeterCategory: string, MeterSubCategory: string, MeterId: string, MeterName: string, MeterRegion: string, UnitOfMeasure: string, Quantity: decimal, EffectivePrice: decimal, CostInBillingCurrency: decimal, CostCenter: string, ConsumedService: string, ResourceId: string, Tags: string, OfferId: string, AdditionalInfo: dynamic, ServiceInfo1: string, ServiceInfo2: string, ResourceName: string, ReservationId: string, ReservationName: string, UnitPrice: decimal, ProductOrderId: string, ProductOrderName: string, Term: string, PublisherType: string, PublisherName: string, ChargeType: string, Frequency: string, PricingModel: string, AvailabilityZone: string, BillingAccountId: string, BillingAccountName: string, BillingCurrencyCode: string, BillingPeriodStartDate: datetime, BillingPeriodEndDate: datetime, BillingProfileId: string, BillingProfileName: string, InvoiceSectionId: string, IsAzureCreditEligible: string, PartNumber: string, PayGPrice: decimal, PlanName: string, ServiceFamily: string) \n .create-or-alter table UsagePreliminaryIngest ingestion csv mapping \"UsagePreliminaryMapping\" ```[{\"Name\":\"InvoiceSectionName\",\"DataType\":\"\",\"Ordinal\":\"0\",\"ConstValue\":null},{\"Name\":\"AccountName\",\"DataType\":\"\",\"Ordinal\":\"1\",\"ConstValue\":null},{\"Name\":\"AccountOwnerId\",\"DataType\":\"\",\"Ordinal\":\"2\",\"ConstValue\":null},{\"Name\":\"SubscriptionId\",\"DataType\":\"\",\"Ordinal\":\"3\",\"ConstValue\":null},{\"Name\":\"SubscriptionName\",\"DataType\":\"\",\"Ordinal\":\"4\",\"ConstValue\":null},{\"Name\":\"ResourceGroup\",\"DataType\":\"\",\"Ordinal\":\"5\",\"ConstValue\":null},{\"Name\":\"ResourceLocation\",\"DataType\":\"\",\"Ordinal\":\"6\",\"ConstValue\":null},{\"Name\":\"Date\",\"DataType\":\"\",\"Ordinal\":\"7\",\"ConstValue\":null},{\"Name\":\"ProductName\",\"DataType\":\"\",\"Ordinal\":\"8\",\"ConstValue\":null},{\"Name\":\"MeterCategory\",\"DataType\":\"\",\"Ordinal\":\"9\",\"ConstValue\":null},{\"Name\":\"MeterSubCategory\",\"DataType\":\"\",\"Ordinal\":\"10\",\"ConstValue\":null},{\"Name\":\"MeterId\",\"DataType\":\"\",\"Ordinal\":\"11\",\"ConstValue\":null},{\"Name\":\"MeterName\",\"DataType\":\"\",\"Ordinal\":\"12\",\"ConstValue\":null},{\"Name\":\"MeterRegion\",\"DataType\":\"\",\"Ordinal\":\"13\",\"ConstValue\":null},{\"Name\":\"UnitOfMeasure\",\"DataType\":\"\",\"Ordinal\":\"14\",\"ConstValue\":null},{\"Name\":\"Quantity\",\"DataType\":\"\",\"Ordinal\":\"15\",\"ConstValue\":null},{\"Name\":\"EffectivePrice\",\"DataType\":\"\",\"Ordinal\":\"16\",\"ConstValue\":null},{\"Name\":\"CostInBillingCurrency\",\"DataType\":\"\",\"Ordinal\":\"17\",\"ConstValue\":null},{\"Name\":\"CostCenter\",\"DataType\":\"\",\"Ordinal\":\"18\",\"ConstValue\":null},{\"Name\":\"ConsumedService\",\"DataType\":\"\",\"Ordinal\":\"19\",\"ConstValue\":null},{\"Name\":\"ResourceId\",\"DataType\":\"\",\"Ordinal\":\"20\",\"ConstValue\":null},{\"Name\":\"Tags\",\"DataType\":\"\",\"Ordinal\":\"21\",\"ConstValue\":null},{\"Name\":\"OfferId\",\"DataType\":\"\",\"Ordinal\":\"22\",\"ConstValue\":null},{\"Name\":\"AdditionalInfo\",\"DataType\":\"\",\"Ordinal\":\"23\",\"ConstValue\":null},{\"Name\":\"ServiceInfo1\",\"DataType\":\"\",\"Ordinal\":\"24\",\"ConstValue\":null},{\"Name\":\"ServiceInfo2\",\"DataType\":\"\",\"Ordinal\":\"25\",\"ConstValue\":null},{\"Name\":\"ResourceName\",\"DataType\":\"\",\"Ordinal\":\"26\",\"ConstValue\":null},{\"Name\":\"ReservationId\",\"DataType\":\"\",\"Ordinal\":\"27\",\"ConstValue\":null},{\"Name\":\"ReservationName\",\"DataType\":\"\",\"Ordinal\":\"28\",\"ConstValue\":null},{\"Name\":\"UnitPrice\",\"DataType\":\"\",\"Ordinal\":\"29\",\"ConstValue\":null},{\"Name\":\"ProductOrderId\",\"DataType\":\"\",\"Ordinal\":\"30\",\"ConstValue\":null},{\"Name\":\"ProductOrderName\",\"DataType\":\"\",\"Ordinal\":\"31\",\"ConstValue\":null},{\"Name\":\"Term\",\"DataType\":\"\",\"Ordinal\":\"32\",\"ConstValue\":null},{\"Name\":\"PublisherType\",\"DataType\":\"\",\"Ordinal\":\"33\",\"ConstValue\":null},{\"Name\":\"PublisherName\",\"DataType\":\"\",\"Ordinal\":\"34\",\"ConstValue\":null},{\"Name\":\"ChargeType\",\"DataType\":\"\",\"Ordinal\":\"35\",\"ConstValue\":null},{\"Name\":\"Frequency\",\"DataType\":\"\",\"Ordinal\":\"36\",\"ConstValue\":null},{\"Name\":\"PricingModel\",\"DataType\":\"\",\"Ordinal\":\"37\",\"ConstValue\":null},{\"Name\":\"AvailabilityZone\",\"DataType\":\"\",\"Ordinal\":\"38\",\"ConstValue\":null},{\"Name\":\"BillingAccountId\",\"DataType\":\"\",\"Ordinal\":\"39\",\"ConstValue\":null},{\"Name\":\"BillingAccountName\",\"DataType\":\"\",\"Ordinal\":\"40\",\"ConstValue\":null},{\"Name\":\"BillingCurrencyCode\",\"DataType\":\"\",\"Ordinal\":\"41\",\"ConstValue\":null},{\"Name\":\"BillingPeriodStartDate\",\"DataType\":\"\",\"Ordinal\":\"42\",\"ConstValue\":null},{\"Name\":\"BillingPeriodEndDate\",\"DataType\":\"\",\"Ordinal\":\"43\",\"ConstValue\":null},{\"Name\":\"BillingProfileId\",\"DataType\":\"\",\"Ordinal\":\"44\",\"ConstValue\":null},{\"Name\":\"BillingProfileName\",\"DataType\":\"\",\"Ordinal\":\"45\",\"ConstValue\":null},{\"Name\":\"InvoiceSectionId\",\"DataType\":\"\",\"Ordinal\":\"46\",\"ConstValue\":null},{\"Name\":\"IsAzureCreditEligible\",\"DataType\":\"\",\"Ordinal\":\"47\",\"ConstValue\":null},{\"Name\":\"PartNumber\",\"DataType\":\"\",\"Ordinal\":\"48\",\"ConstValue\":null},{\"Name\":\"PayGPrice\",\"DataType\":\"\",\"Ordinal\":\"49\",\"ConstValue\":null},{\"Name\":\"PlanName\",\"DataType\":\"\",\"Ordinal\":\"50\",\"ConstValue\":null},{\"Name\":\"ServiceFamily\",\"DataType\":\"\",\"Ordinal\":\"51\",\"ConstValue\":null}]``` \n .create-or-alter function IngestToUsagePreliminary() { UsagePreliminaryIngest | extend Tags = todynamic(strcat(\"{\", Tags, \"}\")), ResourceId = tolower(ResourceId) } \n .create-merge table UsagePreliminary (InvoiceSectionName: string, AccountName: string, AccountOwnerId: string, SubscriptionId: string, SubscriptionName: string, ResourceGroup: string, ResourceLocation: string, Date: datetime, ProductName: string, MeterCategory: string, MeterSubCategory: string, MeterId: string, MeterName: string, MeterRegion: string, UnitOfMeasure: string, Quantity: decimal, EffectivePrice: decimal, CostInBillingCurrency: decimal, CostCenter: string, ConsumedService: string, ResourceId: string, Tags: dynamic, OfferId: string, AdditionalInfo: dynamic, ServiceInfo1: string, ServiceInfo2: string, ResourceName: string, ReservationId: string, ReservationName: string, UnitPrice: decimal, ProductOrderId: string, ProductOrderName: string, Term: string, PublisherType: string, PublisherName: string, ChargeType: string, Frequency: string, PricingModel: string, AvailabilityZone: string, BillingAccountId: string, BillingAccountName: string, BillingCurrencyCode: string, BillingPeriodStartDate: datetime, BillingPeriodEndDate: datetime, BillingProfileId: string, BillingProfileName: string, InvoiceSectionId: string, IsAzureCreditEligible: string, PartNumber: string, PayGPrice: decimal, PlanName: string, ServiceFamily: string)  \n .alter-merge table UsagePreliminaryIngest policy retention softdelete = timespan(0) recoverability = disabled \n .alter table UsagePreliminary policy update ```[{\"IsEnabled\": true, \"Source\": \"UsagePreliminaryIngest\", \"Query\": \"IngestToUsagePreliminary()\", \"IsTransactional\": true, \"PropagateIngestionProperties\": true}]``` \n .create-merge table UsageIngest (InvoiceSectionName: string, AccountName: string, AccountOwnerId: string, SubscriptionId: string, SubscriptionName: string, ResourceGroup: string, ResourceLocation: string, Date: datetime, ProductName: string, MeterCategory: string, MeterSubCategory: string, MeterId: string, MeterName: string, MeterRegion: string, UnitOfMeasure: string, Quantity: decimal, EffectivePrice: decimal, CostInBillingCurrency: decimal, CostCenter: string, ConsumedService: string, ResourceId: string, Tags: string, OfferId: string, AdditionalInfo: dynamic, ServiceInfo1: string, ServiceInfo2: string, ResourceName: string, ReservationId: string, ReservationName: string, UnitPrice: decimal, ProductOrderId: string, ProductOrderName: string, Term: string, PublisherType: string, PublisherName: string, ChargeType: string, Frequency: string, PricingModel: string, AvailabilityZone: string, BillingAccountId: string, BillingAccountName: string, BillingCurrencyCode: string, BillingPeriodStartDate: datetime, BillingPeriodEndDate: datetime, BillingProfileId: string, BillingProfileName: string, InvoiceSectionId: string, IsAzureCreditEligible: string, PartNumber: string, PayGPrice: decimal, PlanName: string, ServiceFamily: string)  \n .create-or-alter table UsageIngest ingestion csv mapping \"UsageMapping\" ```[{\"Name\":\"InvoiceSectionName\",\"DataType\":\"\",\"Ordinal\":\"0\",\"ConstValue\":null},{\"Name\":\"AccountName\",\"DataType\":\"\",\"Ordinal\":\"1\",\"ConstValue\":null},{\"Name\":\"AccountOwnerId\",\"DataType\":\"\",\"Ordinal\":\"2\",\"ConstValue\":null},{\"Name\":\"SubscriptionId\",\"DataType\":\"\",\"Ordinal\":\"3\",\"ConstValue\":null},{\"Name\":\"SubscriptionName\",\"DataType\":\"\",\"Ordinal\":\"4\",\"ConstValue\":null},{\"Name\":\"ResourceGroup\",\"DataType\":\"\",\"Ordinal\":\"5\",\"ConstValue\":null},{\"Name\":\"ResourceLocation\",\"DataType\":\"\",\"Ordinal\":\"6\",\"ConstValue\":null},{\"Name\":\"Date\",\"DataType\":\"\",\"Ordinal\":\"7\",\"ConstValue\":null},{\"Name\":\"ProductName\",\"DataType\":\"\",\"Ordinal\":\"8\",\"ConstValue\":null},{\"Name\":\"MeterCategory\",\"DataType\":\"\",\"Ordinal\":\"9\",\"ConstValue\":null},{\"Name\":\"MeterSubCategory\",\"DataType\":\"\",\"Ordinal\":\"10\",\"ConstValue\":null},{\"Name\":\"MeterId\",\"DataType\":\"\",\"Ordinal\":\"11\",\"ConstValue\":null},{\"Name\":\"MeterName\",\"DataType\":\"\",\"Ordinal\":\"12\",\"ConstValue\":null},{\"Name\":\"MeterRegion\",\"DataType\":\"\",\"Ordinal\":\"13\",\"ConstValue\":null},{\"Name\":\"UnitOfMeasure\",\"DataType\":\"\",\"Ordinal\":\"14\",\"ConstValue\":null},{\"Name\":\"Quantity\",\"DataType\":\"\",\"Ordinal\":\"15\",\"ConstValue\":null},{\"Name\":\"EffectivePrice\",\"DataType\":\"\",\"Ordinal\":\"16\",\"ConstValue\":null},{\"Name\":\"CostInBillingCurrency\",\"DataType\":\"\",\"Ordinal\":\"17\",\"ConstValue\":null},{\"Name\":\"CostCenter\",\"DataType\":\"\",\"Ordinal\":\"18\",\"ConstValue\":null},{\"Name\":\"ConsumedService\",\"DataType\":\"\",\"Ordinal\":\"19\",\"ConstValue\":null},{\"Name\":\"ResourceId\",\"DataType\":\"\",\"Ordinal\":\"20\",\"ConstValue\":null},{\"Name\":\"Tags\",\"DataType\":\"\",\"Ordinal\":\"21\",\"ConstValue\":null},{\"Name\":\"OfferId\",\"DataType\":\"\",\"Ordinal\":\"22\",\"ConstValue\":null},{\"Name\":\"AdditionalInfo\",\"DataType\":\"\",\"Ordinal\":\"23\",\"ConstValue\":null},{\"Name\":\"ServiceInfo1\",\"DataType\":\"\",\"Ordinal\":\"24\",\"ConstValue\":null},{\"Name\":\"ServiceInfo2\",\"DataType\":\"\",\"Ordinal\":\"25\",\"ConstValue\":null},{\"Name\":\"ResourceName\",\"DataType\":\"\",\"Ordinal\":\"26\",\"ConstValue\":null},{\"Name\":\"ReservationId\",\"DataType\":\"\",\"Ordinal\":\"27\",\"ConstValue\":null},{\"Name\":\"ReservationName\",\"DataType\":\"\",\"Ordinal\":\"28\",\"ConstValue\":null},{\"Name\":\"UnitPrice\",\"DataType\":\"\",\"Ordinal\":\"29\",\"ConstValue\":null},{\"Name\":\"ProductOrderId\",\"DataType\":\"\",\"Ordinal\":\"30\",\"ConstValue\":null},{\"Name\":\"ProductOrderName\",\"DataType\":\"\",\"Ordinal\":\"31\",\"ConstValue\":null},{\"Name\":\"Term\",\"DataType\":\"\",\"Ordinal\":\"32\",\"ConstValue\":null},{\"Name\":\"PublisherType\",\"DataType\":\"\",\"Ordinal\":\"33\",\"ConstValue\":null},{\"Name\":\"PublisherName\",\"DataType\":\"\",\"Ordinal\":\"34\",\"ConstValue\":null},{\"Name\":\"ChargeType\",\"DataType\":\"\",\"Ordinal\":\"35\",\"ConstValue\":null},{\"Name\":\"Frequency\",\"DataType\":\"\",\"Ordinal\":\"36\",\"ConstValue\":null},{\"Name\":\"PricingModel\",\"DataType\":\"\",\"Ordinal\":\"37\",\"ConstValue\":null},{\"Name\":\"AvailabilityZone\",\"DataType\":\"\",\"Ordinal\":\"38\",\"ConstValue\":null},{\"Name\":\"BillingAccountId\",\"DataType\":\"\",\"Ordinal\":\"39\",\"ConstValue\":null},{\"Name\":\"BillingAccountName\",\"DataType\":\"\",\"Ordinal\":\"40\",\"ConstValue\":null},{\"Name\":\"BillingCurrencyCode\",\"DataType\":\"\",\"Ordinal\":\"41\",\"ConstValue\":null},{\"Name\":\"BillingPeriodStartDate\",\"DataType\":\"\",\"Ordinal\":\"42\",\"ConstValue\":null},{\"Name\":\"BillingPeriodEndDate\",\"DataType\":\"\",\"Ordinal\":\"43\",\"ConstValue\":null},{\"Name\":\"BillingProfileId\",\"DataType\":\"\",\"Ordinal\":\"44\",\"ConstValue\":null},{\"Name\":\"BillingProfileName\",\"DataType\":\"\",\"Ordinal\":\"45\",\"ConstValue\":null},{\"Name\":\"InvoiceSectionId\",\"DataType\":\"\",\"Ordinal\":\"46\",\"ConstValue\":null},{\"Name\":\"IsAzureCreditEligible\",\"DataType\":\"\",\"Ordinal\":\"47\",\"ConstValue\":null},{\"Name\":\"PartNumber\",\"DataType\":\"\",\"Ordinal\":\"48\",\"ConstValue\":null},{\"Name\":\"PayGPrice\",\"DataType\":\"\",\"Ordinal\":\"49\",\"ConstValue\":null},{\"Name\":\"PlanName\",\"DataType\":\"\",\"Ordinal\":\"50\",\"ConstValue\":null},{\"Name\":\"ServiceFamily\",\"DataType\":\"\",\"Ordinal\":\"51\",\"ConstValue\":null}]``` \n .create function IngestToUsage() { UsageIngest | extend Tags = todynamic(strcat(\"{\", Tags, \"}\")), ResourceId = tolower(ResourceId)} \n .create-merge table Usage (InvoiceSectionName: string, AccountName: string, AccountOwnerId: string, SubscriptionId: string, SubscriptionName: string, ResourceGroup: string, ResourceLocation: string, Date: datetime, ProductName: string, MeterCategory: string, MeterSubCategory: string, MeterId: string, MeterName: string, MeterRegion: string, UnitOfMeasure: string, Quantity: decimal, EffectivePrice: decimal, CostInBillingCurrency: decimal, CostCenter: string, ConsumedService: string, ResourceId: string, Tags: dynamic, OfferId: string, AdditionalInfo: dynamic, ServiceInfo1: string, ServiceInfo2: string, ResourceName: string, ReservationId: string, ReservationName: string, UnitPrice: decimal, ProductOrderId: string, ProductOrderName: string, Term: string, PublisherType: string, PublisherName: string, ChargeType: string, Frequency: string, PricingModel: string, AvailabilityZone: string, BillingAccountId: string, BillingAccountName: string, BillingCurrencyCode: string, BillingPeriodStartDate: datetime, BillingPeriodEndDate: datetime, BillingProfileId: string, BillingProfileName: string, InvoiceSectionId: string, IsAzureCreditEligible: string, PartNumber: string, PayGPrice: decimal, PlanName: string, ServiceFamily: string) \n .alter-merge table UsageIngest policy retention softdelete = timespan(0) recoverability = disabled \n .alter table Usage policy update ```[{\"IsEnabled\": true, \"Source\": \"UsageIngest\", \"Query\": \"IngestToUsage()\", \"IsTransactional\": true, \"PropagateIngestionProperties\": true}]``` \n .add table UsagePreliminaryIngest ingestors (\"aadapp=', parameters('kustoIngestClientId'), '\") \n.add table UsagePreliminary admins (\"aadapp=', parameters('kustoIngestClientId'), '\") \n.add table UsageIngest ingestors (\"aadapp=', parameters('kustoIngestClientId'), '\") \n.add table Usage admins (\"aadapp=', parameters('kustoIngestClientId'), '\")')]"   
    },
    "resources": [
        {
            "type": "Microsoft.Kusto/clusters",
            "apiVersion": "2019-05-15",
            "name": "[parameters('kustoClusterName')]",
            "location": "[resourceGroup().location]",
            "sku": {
                "name": "[if(parameters('preProduction'), 'Dev(No SLA)_Standard_E2a_v4', 'Standard_E8as_v5+1TB_PS')]",
                "tier": "[if(parameters('preProduction'), 'Basic', 'Standard')]",
                "capacity": "[if(parameters('preProduction'), '1', '2')]"
            },
            "properties": {
                "enableDiskEncryption": false,
                "enableStreamingIngest": false
            }
        },
        {
            "name": "[concat(parameters('kustoClusterName'), '/', parameters('kustoDatabaseName'))]",
            "type": "Microsoft.Kusto/clusters/databases",
            "apiVersion": "2019-05-15",
            "location": "[resourceGroup().location]",
            "dependsOn": [
                "[parameters('kustoClusterName')]"
            ],
            "properties": {
                "softDeletePeriodInDays": 1825,
                "hotCachePeriodInDays": 90
            }
        },
        {
            "type": "Microsoft.Kusto/Clusters/Databases/Scripts",
            "apiVersion": "2022-02-01",
            "name": "[concat(parameters('kustoClusterName'), '/', parameters('kustoDatabaseName'), '/costmanagement')]",
            "properties": {
                "scriptContent": "[variables('kqlScript')]",
                "continueOnErrors": false,
                "forceUpdateTag": "[parameters('forceUpdateTag')]"
            },
            "dependsOn": [
                "[parameters('kustoDatabaseName')]"
            ]
        },
        {
            "type": "Microsoft.Storage/storageAccounts",
            "apiVersion": "2019-06-01",
            "name": "[parameters('storageAccountName')]",
            "location": "[resourceGroup().location]",
            "sku": {
                "name": "Standard_LRS",
                "tier": "Standard"
            },
            "kind": "StorageV2",
            "properties": {
                "supportsHttpsTrafficOnly": true,
                "accessTier": "[if(parameters('preProduction'), 'Hot', 'Cool')]"
            }
        },
        {
            "type": "Microsoft.Storage/storageAccounts/blobServices/containers",
            "apiVersion": "2019-06-01",
            "name": "[concat(parameters('storageAccountName'), '/default/usage-final')]",
            "dependsOn": [
                "[parameters('storageAccountName')]"
            ],
            "properties": {
                "publicAccess": "None"
            }
        },
        {
            "type": "Microsoft.Storage/storageAccounts/blobServices/containers/providers/roleAssignments",
            "name": "[concat(parameters('storageAccountName'),'/default/usage-final/Microsoft.Authorization/', guid(resourceGroup().id, 'roleDfToCf'))]",
            "apiVersion": "2018-07-01",
            "properties": {
                "principalId": "[reference(parameters('dataFactoryName'), '2018-06-01', 'Full').identity.principalId]",
                "roleDefinitionId": "[concat(subscription().id, '/providers/Microsoft.Authorization/roleDefinitions/', 'ba92f5b4-2d11-453d-a403-e96b0029c9fe')]"
            },
            "dependsOn": [
                "usage-final",
                "pipeline_ingest_usage_final"
            ]
        },
        {
            "type": "Microsoft.Storage/storageAccounts/blobServices/containers",
            "apiVersion": "2019-06-01",
            "name": "[concat(parameters('storageAccountName'), '/default/usage-preliminary')]",
            "dependsOn": [
                "[parameters('storageAccountName')]"
            ],
            "properties": {
                "publicAccess": "None"
            }
        },
        {
            "type": "Microsoft.Storage/storageAccounts/blobServices/containers/providers/roleAssignments",
            "name": "[concat(parameters('storageAccountName'),'/default/usage-preliminary/Microsoft.Authorization/', guid(resourceGroup().id, 'roleDfToCp'))]",
            "apiVersion": "2018-07-01",
            "properties": {
                "principalId": "[reference(parameters('dataFactoryName'), '2018-06-01', 'Full').identity.principalId]",
                "roleDefinitionId": "[concat(subscription().id, '/providers/Microsoft.Authorization/roleDefinitions/', 'ba92f5b4-2d11-453d-a403-e96b0029c9fe')]"
            },
            "dependsOn": [
                "usage-preliminary",
                "pipeline_ingest_usage_preliminary"
            ]
        },
        {
            "name": "[parameters('dataFactoryName')]",
            "apiVersion": "2018-06-01",
            "type": "Microsoft.DataFactory/factories",
            "location": "[resourceGroup().location]",
            "identity": {
                "type": "SystemAssigned"
            },
            "properties": {
            }
        },
        {
            "name": "[concat(parameters('dataFactoryName'), '/link_blob_azmeta_account')]",
            "type": "Microsoft.DataFactory/factories/linkedServices",
            "apiVersion": "2018-06-01",
            "properties": {
                "annotations": [
                ],
                "type": "AzureBlobStorage",
                "typeProperties": {
                    "serviceEndpoint": "[reference(parameters('storageAccountName'), '2019-06-01').primaryEndpoints.blob]"
                }
            },
            "dependsOn": [
                "[parameters('dataFactoryName')]"
            ]
        },
        {
            "name": "[concat(parameters('dataFactoryName'), '/link_kusto_azmeta')]",
            "type": "Microsoft.DataFactory/factories/linkedServices",
            "apiVersion": "2018-06-01",
            "properties": {
                "type": "AzureDataExplorer",
                "typeProperties": {
                    "endpoint": "[reference(parameters('kustoClusterName'), '2019-05-15').uri]",
                    "tenant": "[subscription().tenantId]",
                    "servicePrincipalId": "[parameters('kustoIngestClientId')]",
                    "servicePrincipalKey": {
                        "type": "SecureString",
                        "value": "[parameters('kustoIngestClientSecret')]"
                    },
                    "database": "[parameters('kustoDatabaseName')]"
                }
            },
            "dependsOn": [
                "[parameters('dataFactoryName')]"
            ]
        },
        {
            "name": "[concat(parameters('dataFactoryName'), '/dataset_kusto_usage_table')]",
            "type": "Microsoft.DataFactory/factories/datasets",
            "apiVersion": "2018-06-01",
            "properties": {
                "linkedServiceName": {
                    "referenceName": "link_kusto_azmeta",
                    "type": "LinkedServiceReference"
                },
                "parameters": {
                    "Table": {
                        "type": "string"
                    }
                },
                "type": "AzureDataExplorerTable",
                "schema": [
                ],
                "typeProperties": {
                    "table": {
                        "value": "@dataset().Table",
                        "type": "Expression"
                    }
                }
            },
            "dependsOn": [
                "link_kusto_azmeta"
            ]
        },
        {
            "name": "[concat(parameters('dataFactoryName'), '/dataset_blob_usage_incoming')]",
            "type": "Microsoft.DataFactory/factories/datasets",
            "apiVersion": "2018-06-01",
            "properties": {
                "linkedServiceName": {
                    "referenceName": "link_blob_azmeta_account",
                    "type": "LinkedServiceReference"
                },
                "parameters": {
                    "Container": {
                        "type": "string"
                    }
                },
                "annotations": [],
                "type": "DelimitedText",
                "typeProperties": {
                    "location": {
                        "type": "AzureBlobStorageLocation",
                        "container": {
                            "value": "@dataset().Container",
                            "type": "Expression"
                        }
                    },
                    "columnDelimiter": ",",
                    "escapeChar": "\"",
                    "firstRowAsHeader": true,
                    "quoteChar": "\""
                },
                "schema": [
                ]
            },
            "dependsOn": [
                "link_blob_azmeta_account"
            ]
        },
        {
            "name": "[concat(parameters('dataFactoryName'), '/dataset_blob_usage_compressed')]",
            "type": "Microsoft.DataFactory/factories/datasets",
            "apiVersion": "2018-06-01",
            "properties": {
                "linkedServiceName": {
                    "referenceName": "link_blob_azmeta_account",
                    "type": "LinkedServiceReference"
                },
                "parameters": {
                    "BlobName": {
                        "type": "string"
                    },
                    "Container": {
                        "type": "string"
                    }
                },
                "annotations": [],
                "type": "DelimitedText",
                "typeProperties": {
                    "location": {
                        "type": "AzureBlobStorageLocation",
                        "fileName": {
                            "value": "@concat(dataset().BlobName, '.csv.gz')",
                            "type": "Expression"
                        },
                        "folderPath": "archive",
                        "container": {
                            "value": "@dataset().Container",
                            "type": "Expression"
                        }
                    },
                    "columnDelimiter": ",",
                    "compressionCodec": "gzip",
                    "compressionLevel": "Optimal",
                    "escapeChar": "\"",
                    "firstRowAsHeader": true,
                    "quoteChar": "\""
                },
                "schema": [
                ]
            },
            "dependsOn": [
                "link_blob_azmeta_account"
            ]
        },
        {
            "name": "[concat(parameters('dataFactoryName'), '/pipeline_ingest_usage_final')]",
            "type": "Microsoft.DataFactory/factories/pipelines",
            "apiVersion": "2018-06-01",
            "properties": {
                "activities": [
                    {
                        "name": "drop_old_preliminary_data",
                        "type": "AzureDataExplorerCommand",
                        "dependsOn": [
                            {
                                "activity": "copy_usage_from_archive_to_table",
                                "dependencyConditions": [
                                    "Succeeded"
                                ]
                            }
                        ],
                        "policy": {
                            "timeout": "7.00:00:00",
                            "retry": 6,
                            "retryIntervalInSeconds": 60,
                            "secureOutput": false,
                            "secureInput": false
                        },
                        "userProperties": [],
                        "typeProperties": {
                            "command": {
                                "value": "@concat('.drop extents <| \n  .show table UsagePreliminary extents \n  | extend Tags = split(Tags, \"\\r\\n\")\n  | where set_has_element(Tags, \"', last(split(pipeline().parameters.BlobPath, '/')),'\")')",
                                "type": "Expression"
                            },
                            "commandTimeout": "00:20:00"
                        },
                        "linkedServiceName": {
                            "referenceName": "link_kusto_azmeta",
                            "type": "LinkedServiceReference"
                        }
                    },
                    {
                        "name": "copy_usage_from_archive_to_table",
                        "type": "Copy",
                        "dependsOn": [
                            {
                                "activity": "compress_incoming",
                                "dependencyConditions": [
                                    "Succeeded"
                                ]
                            }
                        ],
                        "policy": {
                            "timeout": "7.00:00:00",
                            "retry": 6,
                            "retryIntervalInSeconds": 60,
                            "secureOutput": false,
                            "secureInput": false
                        },
                        "userProperties": [],
                        "typeProperties": {
                            "source": {
                                "type": "DelimitedTextSource",
                                "storeSettings": {
                                    "type": "AzureBlobStorageReadSettings",
                                    "recursive": true,
                                    "enablePartitionDiscovery": false
                                },
                                "formatSettings": {
                                    "type": "DelimitedTextReadSettings"
                                }
                            },
                            "sink": {
                                "type": "AzureDataExplorerSink",
                                "ingestionMappingName": "UsageMapping",
                                "additionalProperties": {
                                    "value": "@concat('{\"tags\":\"[\\\"', last(split(pipeline().parameters.BlobPath, '/')), '\\\", \\\"', pipeline().RunId, '\\\"]\"}')",
                                    "type": "Expression"
                                }
                            },
                            "enableStaging": false,
                            "translator": "[variables('usageTableTranslator')]"
                        },
                        "inputs": [
                            {
                                "referenceName": "dataset_blob_usage_compressed",
                                "type": "DatasetReference",
                                "parameters": {
                                    "BlobName": "@last(split(pipeline().parameters.BlobPath, '/'))",
                                    "Container": "usage-final"
                                }
                            }
                        ],
                        "outputs": [
                            {
                                "referenceName": "dataset_kusto_usage_table",
                                "type": "DatasetReference",
                                "parameters": {
                                    "Table": "UsageIngest"
                                }
                            }
                        ]
                    },
                    {
                        "name": "compress_incoming",
                        "type": "Copy",
                        "dependsOn": [],
                        "policy": {
                            "timeout": "7.00:00:00",
                            "retry": 6,
                            "retryIntervalInSeconds": 60,
                            "secureOutput": false,
                            "secureInput": false
                        },
                        "userProperties": [],
                        "typeProperties": {
                            "source": {
                                "type": "DelimitedTextSource",
                                "storeSettings": {
                                    "type": "AzureBlobStorageReadSettings",
                                    "recursive": true,
                                    "enablePartitionDiscovery": false,
                                    "prefix": {
                                        "value": "@{concat(pipeline().parameters.BlobPath, '/', pipeline().parameters.BlobName)}",
                                        "type": "Expression"
                                    }
                                },
                                "formatSettings": {
                                    "type": "DelimitedTextReadSettings"
                                }
                            },
                            "sink": {
                                "type": "DelimitedTextSink",
                                "storeSettings": {
                                    "type": "AzureBlobStorageWriteSettings",
                                    "copyBehavior": "MergeFiles"
                                },
                                "formatSettings": {
                                    "type": "DelimitedTextWriteSettings",
                                    "quoteAllText": true,
                                    "fileExtension": ".gz"
                                }
                            },
                            "enableStaging": false
                        },
                        "inputs": [
                            {
                                "referenceName": "dataset_blob_usage_incoming",
                                "type": "DatasetReference",
                                "parameters": {
                                    "Container": "usage-final"
                                }
                            }
                        ],
                        "outputs": [
                            {
                                "referenceName": "dataset_blob_usage_compressed",
                                "type": "DatasetReference",
                                "parameters": {
                                    "BlobName": {
                                        "value": "@last(split(pipeline().parameters.BlobPath, '/'))",
                                        "type": "Expression"
                                    },
                                    "Container": "usage-final"
                                }
                            }
                        ]
                    }
                ],
                "parameters": {
                    "BlobPath": {
                        "type": "string"
                    },
                    "BlobName": {
                        "type": "string"
                    }
                },
                "annotations": [
                ]
            },
            "dependsOn": [
                "dataset_blob_usage_compressed",
                "dataset_kusto_usage_table",
                "dataset_blob_usage_incoming"
            ]
        },
        {
            "name": "[concat(parameters('dataFactoryName'), '/pipeline_ingest_usage_preliminary')]",
            "type": "Microsoft.DataFactory/factories/pipelines",
            "apiVersion": "2018-06-01",
            "properties": {
                "activities": [
                    {
                        "name": "copy_usage_to_table",
                        "type": "Copy",
                        "dependsOn": [],
                        "policy": {
                            "timeout": "7.00:00:00",
                            "retry": 6,
                            "retryIntervalInSeconds": 60,
                            "secureOutput": false,
                            "secureInput": false
                        },
                        "userProperties": [],
                        "typeProperties": {
                            "source": {
                                "type": "DelimitedTextSource",
                                "storeSettings": {
                                    "type": "AzureBlobStorageReadSettings",
                                    "recursive": true,
                                    "enablePartitionDiscovery": false,
                                    "prefix": {
                                        "value": "@{concat(pipeline().parameters.BlobPath, '/', pipeline().parameters.BlobName)}",
                                        "type": "Expression"
                                    }
                                },
                                "formatSettings": {
                                    "type": "DelimitedTextReadSettings"
                                }
                            },
                            "sink": {
                                "type": "AzureDataExplorerSink",
                                "ingestionMappingName": "UsagePreliminaryMapping",
                                "additionalProperties": {
                                    "value": "@concat('{\"tags\":\"[\\\"', last(split(pipeline().parameters.BlobPath, '/')), '\\\", \\\"drop-by:', pipeline().RunId, '\\\"]\"}')",
                                    "type": "Expression"
                                }
                            },
                            "enableStaging": false,
                            "translator": "[variables('usageTableTranslator')]"
                        },
                        "inputs": [
                            {
                                "referenceName": "dataset_blob_usage_incoming",
                                "type": "DatasetReference",
                                "parameters": {
                                    "Container": "usage-preliminary"
                                }
                            }
                        ],
                        "outputs": [
                            {
                                "referenceName": "dataset_kusto_usage_table",
                                "type": "DatasetReference",
                                "parameters": {
                                    "Table": "UsagePreliminaryIngest"
                                }
                            }
                        ]
                    },
                    {
                        "name": "drop_old_data",
                        "type": "AzureDataExplorerCommand",
                        "dependsOn": [
                            {
                                "activity": "copy_usage_to_table",
                                "dependencyConditions": [
                                    "Succeeded"
                                ]
                            }
                        ],
                        "policy": {
                            "timeout": "7.00:00:00",
                            "retry": 6,
                            "retryIntervalInSeconds": 60,
                            "secureOutput": false,
                            "secureInput": false
                        },
                        "userProperties": [],
                        "typeProperties": {
                            "command": {
                                "value": "@concat('.drop extents <| \n  .show table UsagePreliminary extents \n  | extend Tags = split(Tags, \"\\r\\n\")\n  | where set_has_element(Tags, \"', last(split(pipeline().parameters.BlobPath, '/')),'\") and not(set_has_element(Tags, \"drop-by:', pipeline().RunId,'\"))')",
                                "type": "Expression"
                            },
                            "commandTimeout": "00:20:00"
                        },
                        "linkedServiceName": {
                            "referenceName": "link_kusto_azmeta",
                            "type": "LinkedServiceReference"
                        }
                    }

                ],
                "parameters": {
                    "BlobPath": {
                        "type": "string"
                    },
                    "BlobName": {
                        "type": "string"
                    }
                },
                "annotations": [
                ]
            },
            "dependsOn": [
                "dataset_kusto_usage_table",
                "dataset_blob_usage_incoming"
            ]
        },
        {
            "condition": "[not(parameters('updating'))]",
            "name": "[concat(parameters('dataFactoryName'), '/trigger_usage_final_amortized')]",
            "type": "Microsoft.DataFactory/factories/triggers",
            "apiVersion": "2018-06-01",
            "properties": {
                "pipelines": [
                    {
                        "pipelineReference": {
                            "referenceName": "pipeline_ingest_usage_final",
                            "type": "PipelineReference"
                        },
                        "parameters": {
                            "BlobPath": "@replace(trigger().outputs.body.folderPath, 'usage-final/', '')",
                            "BlobName": "@trigger().outputs.body.fileName"
                        }
                    }
                ],
                "type": "BlobEventsTrigger",
                "typeProperties": {
                    "blobPathBeginsWith": "/usage-final/blobs/export/finalamortized",
                    "blobPathEndsWith": ".csv",
                    "ignoreEmptyBlobs": true,
                    "scope": "[resourceId('Microsoft.Storage/storageAccounts', parameters('storageAccountName'))]",
                    "events": [
                        "Microsoft.Storage.BlobCreated"
                    ]
                }
            },
            "dependsOn": [
                "pipeline_ingest_usage_final"
            ]
        },
        {
            "condition": "[not(parameters('updating'))]",
            "name": "[concat(parameters('dataFactoryName'), '/trigger_usage_final_amortized_onetime')]",
            "type": "Microsoft.DataFactory/factories/triggers",
            "apiVersion": "2018-06-01",
            "properties": {
                "pipelines": [
                    {
                        "pipelineReference": {
                            "referenceName": "pipeline_ingest_usage_final",
                            "type": "PipelineReference"
                        },
                        "parameters": {
                            "BlobPath": "@replace(trigger().outputs.body.folderPath, 'usage-final/', '')",
                            "BlobName": "@trigger().outputs.body.fileName"
                        }
                    }
                ],
                "type": "BlobEventsTrigger",
                "typeProperties": {
                    "blobPathBeginsWith": "/usage-final/blobs/export/onetime",
                    "blobPathEndsWith": ".csv",
                    "ignoreEmptyBlobs": true,
                    "scope": "[resourceId('Microsoft.Storage/storageAccounts', parameters('storageAccountName'))]",
                    "events": [
                        "Microsoft.Storage.BlobCreated"
                    ]
                }
            },
            "dependsOn": [
                "pipeline_ingest_usage_final"
            ]
        },
        {
            "condition": "[not(parameters('updating'))]",
            "name": "[concat(parameters('dataFactoryName'), '/trigger_usage_preliminary_amortized')]",
            "type": "Microsoft.DataFactory/factories/triggers",
            "apiVersion": "2018-06-01",
            "properties": {
                "pipelines": [
                    {
                        "pipelineReference": {
                            "referenceName": "pipeline_ingest_usage_preliminary",
                            "type": "PipelineReference"
                        },
                        "parameters": {
                            "BlobPath": "@replace(trigger().outputs.body.folderPath, 'usage-preliminary/', '')",
                            "BlobName": "@trigger().outputs.body.fileName"
                        }
                    }
                ],
                "type": "BlobEventsTrigger",
                "typeProperties": {
                    "blobPathBeginsWith": "/usage-preliminary/blobs/export/preliminaryamortized",
                    "blobPathEndsWith": ".csv",
                    "ignoreEmptyBlobs": true,
                    "scope": "[resourceId('Microsoft.Storage/storageAccounts', parameters('storageAccountName'))]",
                    "events": [
                        "Microsoft.Storage.BlobCreated"
                    ]
                }
            },
            "dependsOn": [
                "pipeline_ingest_usage_preliminary"
            ]
        },
        {
            "type": "Microsoft.Resources/deploymentScripts",
            "apiVersion": "2019-10-01-preview",
            "name": "startUsageTriggers",
            "location": "[resourceGroup().location]",
            "kind": "AzurePowerShell",
            "identity": {
                "type": "UserAssigned",
                "userAssignedIdentities": {
                    "[parameters('deploymentIdentity')]": {}
                }
            },
            "properties": {
                "forceUpdateTag": "1",
                "azPowerShellVersion": "4.2",
                "environmentVariables": [
                    {
                        "name": "AZMETA_RG",
                        "value": "[resourceGroup().name]"
                    },
                    {
                        "name": "AZMETA_DATAFACTORY",
                        "value": "[parameters('dataFactoryName')]"
                    },
                    {
                        "name": "AZMETA_TRIGGER_FINAL",
                        "value": "trigger_usage_final_amortized"
                    },
                    {
                        "name": "AZMETA_TRIGGER_FINAL_ONETIME",
                        "value": "trigger_usage_final_amortized_onetime"
                    },
                    {
                        "name": "AZMETA_TRIGGER_PRELIMINARY",
                        "value": "trigger_usage_preliminary_amortized"
                    }
                ],
                "scriptContent": "@($env:AZMETA_TRIGGER_FINAL, $env:AZMETA_TRIGGER_FINAL_ONETIME, $env:AZMETA_TRIGGER_PRELIMINARY) | ForEach-Object { Start-AzDataFactoryV2Trigger -Name $_ -ResourceGroupName $env:AZMETA_RG -DataFactoryName $env:AZMETA_DATAFACTORY -Force; }",
                "timeout": "PT15M",
                "cleanupPreference": "OnSuccess",
                "retentionInterval": "P1D"
            },
            "dependsOn": [
                "trigger_usage_final_amortized",
                "trigger_usage_preliminary_amortized",
                "trigger_usage_final_amortized_onetime"
            ]
        }
    ],
    "outputs": {
        "usageSubscription": {
            "type": "string",
            "value": "[subscription().subscriptionId]"
        },
        "usageResourceGroup": {
            "type": "string",
            "value": "[resourceGroup().name]"
        },
        "usageDataFactory": {
            "type": "string",
            "value": "[parameters('dataFactoryName')]"
        },
        "usageStorageAccount": {
            "type": "string",
            "value": "[parameters('storageAccountName')]"
        },
        "usageKustoCluster": {
            "type": "string",
            "value": "[parameters('kustoClusterName')]"
        },
        "usageKustoClusterUrl": {
            "type": "string",
            "value": "[reference(parameters('kustoClusterName'), '2019-05-15').uri]"
        }
    }
}